fastlz_native/__init__.py
fastlz_native/decompress.py
pyfastlz_native-0.0.1.dist-info/LICENSE
pyfastlz_native-0.0.1.dist-info/METADATA
pyfastlz_native-0.0.1.dist-info/WHEEL
pyfastlz_native-0.0.1.dist-info/top_level.txt
pyfastlz_native-0.0.1.dist-info/RECORD
