Metadata-Version: 2.1
Name: pyfastlz-native
Version: 0.0.1
Summary: FastLZ implementation in native python3
Author-email: Oscar Diaz <odiaz@ieee.org>
Classifier: Programming Language :: Python :: 3
Classifier: License :: OSI Approved :: MIT License
Classifier: Operating System :: OS Independent
Requires-Python: >=3.9
License-File: LICENSE
